LICENSE
README.md
pyproject.toml
setup.py
shedok/__init__.py
shedok/shedule.py
shedok/sheduler.py
shedok.egg-info/PKG-INFO
shedok.egg-info/SOURCES.txt
shedok.egg-info/dependency_links.txt
shedok.egg-info/not-zip-safe
shedok.egg-info/top_level.txt