Metadata-Version: 2.1
Name: shedok
Version: 0.1.1
Summary: Pending tasks management
Author-email: Mrybs <mrybs2@gmail.com>
Project-URL: Homepage, https://github.com/mrybs/shedok
Project-URL: Bug Tracker, https://github.com/mrybs/shedok/issues
Classifier: Programming Language :: Python :: 3
Classifier: License :: OSI Approved :: MIT License
Classifier: Operating System :: OS Independent
Requires-Python: >=3.7
License-File: LICENSE
